CTkScrollableDropdownPP/__init__.py
CTkScrollableDropdownPP/ctk_scrollable_dropdown.py
ctkscrollabledropdownpp-2.2.dist-info/licenses/LICENSE
ctkscrollabledropdownpp-2.2.dist-info/METADATA
ctkscrollabledropdownpp-2.2.dist-info/WHEEL
ctkscrollabledropdownpp-2.2.dist-info/top_level.txt
ctkscrollabledropdownpp-2.2.dist-info/RECORD
