Metadata-Version: 2.4
Name: CTkScrollableDropdownPP
Version: 2.2
Summary: Enhanced CTkScrollableDropdown with pagination, search and groups support
Author: PLauncher-Team, Akash Bora
License: MIT
Project-URL: Homepage, https://github.com/PLauncher-Team/CTkScrollableDropdownPP
Project-URL: Original, https://github.com/Akascape/CTkScrollableDropdown
Keywords: customtkinter,dropdown,pagination,search,groups
Classifier: Programming Language :: Python :: 3
Classifier: Operating System :: OS Independent
Requires-Python: >=3.8
License-File: LICENSE
Requires-Dist: customtkinter>=5.2.0
Requires-Dist: pillow
Dynamic: license-file
